onesaitplatform_orange3-1.1.1-py3.7-nspkg.pth
orangecontrib/onesaitplatform/__init__.py
orangecontrib/onesaitplatform/tests/__init__.py
orangecontrib/onesaitplatform/tests/test_example.py
orangecontrib/onesaitplatform/utils/__init__.py
orangecontrib/onesaitplatform/utils/dataconversion.py
orangecontrib/onesaitplatform/widgets/__init__.py
orangecontrib/onesaitplatform/widgets/debug.py
orangecontrib/onesaitplatform/widgets/ospclient.py
orangecontrib/onesaitplatform/widgets/ospflatdata.py
orangecontrib/onesaitplatform/widgets/ospinsert.py
orangecontrib/onesaitplatform/widgets/ospquery.py
orangecontrib/onesaitplatform/widgets/ospuploadmodel.py
orangecontrib/onesaitplatform/widgets/icons/category.svg
orangecontrib/onesaitplatform/widgets/icons/client.svg
orangecontrib/onesaitplatform/widgets/icons/file_manager_upload.svg
orangecontrib/onesaitplatform/widgets/icons/flat_data.svg
orangecontrib/onesaitplatform/widgets/icons/iot_client_insert.svg
orangecontrib/onesaitplatform/widgets/icons/iot_client_query.svg
onesaitplatform_orange3-1.1.1.dist-info/METADATA
onesaitplatform_orange3-1.1.1.dist-info/WHEEL
onesaitplatform_orange3-1.1.1.dist-info/entry_points.txt
onesaitplatform_orange3-1.1.1.dist-info/namespace_packages.txt
onesaitplatform_orange3-1.1.1.dist-info/top_level.txt
onesaitplatform_orange3-1.1.1.dist-info/RECORD
