Metadata-Version: 2.1
Name: onesaitplatform-orange3
Version: 1.1.1
Summary: Add-on containing onesaitplatform widgets
Home-page: UNKNOWN
License: Apache v2.0
Keywords: onesaitplatform orange3
Platform: UNKNOWN
Requires-Dist: Orange3
Requires-Dist: onesaitplatform-client-services (>=1.2.3)
